bqme/__init__.py
bqme/_settings.py
bqme/distributions.py
bqme/fit_object.py
bqme/models.py
bqme/settings.py
bqme/stan_code_template.stan
bqme/variables.py
test/__init__.py
test/test_distributions.py
test/test_models.py
test/test_variables.py
test/filled_templates/os_normal.stan
tests/__init__.py
tests/conftest.py
tests/test_distributions.py
tests/test_fit_object.py
tests/test_models.py
tests/test_variables.py
tests/filled_templates/os_gamma.stan
tests/filled_templates/os_lognormal.stan
tests/filled_templates/os_normal.stan
tests/filled_templates/os_weibull.stan
bqme-0.2.0.dist-info/LICENSE.txt
bqme-0.2.0.dist-info/METADATA
bqme-0.2.0.dist-info/WHEEL
bqme-0.2.0.dist-info/top_level.txt
bqme-0.2.0.dist-info/RECORD
