Metadata-Version: 2.1
Name: bqme
Version: 0.2.0
Summary: Bayesian Quanile Matching Estimation
Home-page: https://github.com/RSNirwan/BQME
Author: Rajbir Singh Nirwan
Author-email: rajbir.nirwan@gmail.com
License: UNKNOWN
Platform: UNKNOWN
Classifier: Programming Language :: Python :: 3
Classifier: License :: OSI Approved :: GNU General Public License v3 (GPLv3)
Classifier: Operating System :: OS Independent
Requires-Python: >=3.7
Requires-Dist: pystan (>=2.19)
Requires-Dist: numpy (>=1.19.2)
Requires-Dist: scipy (>=1.5.2)
Provides-Extra: dev
Requires-Dist: pytest (>=6.0) ; extra == 'dev'
Requires-Dist: pytest-cov (==2.10.1) ; extra == 'dev'
Requires-Dist: sphinx (==3.2.1) ; extra == 'dev'
Requires-Dist: sphinx-rtd-theme (==0.5.0) ; extra == 'dev'
Requires-Dist: recommonmark (==0.6.0) ; extra == 'dev'
